[1,["07rjN2TX5Gsb19qLtUHFvM","485pZdoVVH74E3GXvlAzv6","baITN7cFpP04aPVYQN+26z","f7m0+BsvJFxo/dyUIndiFs","b4gWDuYqxElZVkQ6pmgW6h"],["_textureSetter","tree1","tree2","tree3","tree4"],["cc.SpriteFrame",["cc.SpriteAtlas",["_name","_spriteFrames"],2,11]],[[1,0,1,2]],[[[{"name":"tree1","rect":[1,633,242,338],"offset":[0,-18],"originalSize":[384,468],"capInsets":[0,0,0,0]}],[0],0,[0],[0],[0]],[[[0,"tree.plist",[{},"tree1",6,0,"tree2",6,1,"tree3",6,2,"tree4",6,3]]],0,0,[0,0,0,0],[1,2,3,4],[1,2,3,4]],[[{"name":"tree4","rect":[1,317,314,314],"offset":[0,0],"originalSize":[384,384],"capInsets":[0,0,0,0]}],[0],0,[0],[0],[0]],[[{"name":"tree2","rect":[245,633,242,338],"offset":[0,-18],"originalSize":[384,468],"capInsets":[0,0,0,0]}],[0],0,[0],[0],[0]],[[{"name":"tree3","rect":[1,1,314,314],"offset":[0,0],"originalSize":[384,384],"capInsets":[0,0,0,0]}],[0],0,[0],[0],[0]]]]