[1,["5d/f24muVBYqvYhJfMpyg/","fe1Ft83NBK45YXY/WkKfSk","1doHW0Bl9PCqeDPpKdAU66"],["_textureSetter","flower1","flower2"],["cc.SpriteFrame",["cc.SpriteAtlas",["_name","_spriteFrames"],2,11]],[[1,0,1,2]],[[[{"name":"flower2","rect":[1,83,38,80],"offset":[0,0],"originalSize":[96,96],"capInsets":[0,0,0,0]}],[0],0,[0],[0],[0]],[[[0,"flower.plist",[{},"flower1",6,0,"flower2",6,1]]],0,0,[0,0],[1,2],[1,2]],[[{"name":"flower1","rect":[1,1,38,80],"offset":[0,0],"originalSize":[96,96],"capInsets":[0,0,0,0]}],[0],0,[0],[0],[0]]]]